etc/monasca/persister-logging.conf
monasca_persister/README.md
monasca_persister/__init__.py
monasca_persister/config.py
monasca_persister/persister.py
monasca_persister/version.py
monasca_persister/conf/__init__.py
monasca_persister/conf/cassandra.py
monasca_persister/conf/elasticsearch.py
monasca_persister/conf/influxdb.py
monasca_persister/conf/kafka_alarm_history.py
monasca_persister/conf/kafka_common.py
monasca_persister/conf/kafka_events.py
monasca_persister/conf/kafka_metrics.py
monasca_persister/conf/repositories.py
monasca_persister/conf/types.py
monasca_persister/conf/zookeeper.py
monasca_persister/hacking/__init__.py
monasca_persister/hacking/checks.py
monasca_persister/kafka/__init__.py
monasca_persister/kafka/confluent_kafka_persister.py
monasca_persister/kafka/legacy_kafka_persister.py
monasca_persister/repositories/__init__.py
monasca_persister/repositories/abstract_repository.py
monasca_persister/repositories/data_points.py
monasca_persister/repositories/persister.py
monasca_persister/repositories/singleton.py
monasca_persister/repositories/utils.py
monasca_persister/repositories/cassandra/__init__.py
monasca_persister/repositories/cassandra/abstract_repository.py
monasca_persister/repositories/cassandra/alarm_state_history_repository.py
monasca_persister/repositories/cassandra/connection_util.py
monasca_persister/repositories/cassandra/metric_batch.py
monasca_persister/repositories/cassandra/metrics_repository.py
monasca_persister/repositories/cassandra/retry_policy.py
monasca_persister/repositories/cassandra/token_range_query_manager.py
monasca_persister/repositories/elasticsearch/__init__.py
monasca_persister/repositories/elasticsearch/events_repository.py
monasca_persister/repositories/influxdb/__init__.py
monasca_persister/repositories/influxdb/abstract_repository.py
monasca_persister/repositories/influxdb/alarm_state_history_repository.py
monasca_persister/repositories/influxdb/line_utils.py
monasca_persister-9.0.0.dist-info/AUTHORS
monasca_persister-9.0.0.dist-info/LICENSE
monasca_persister-9.0.0.dist-info/METADATA
monasca_persister-9.0.0.dist-info/WHEEL
monasca_persister-9.0.0.dist-info/entry_points.txt
monasca_persister-9.0.0.dist-info/pbr.json
monasca_persister-9.0.0.dist-info/top_level.txt
monasca_persister-9.0.0.dist-info/RECORD
