Metadata-Version: 2.1
Name: monasca-persister
Version: 9.0.0
Summary: Moves metrics and alarm state transitions from the Message Queue to the Metrics and Alarms database.
Home-page: https://opendev.org/openstack/monasca-persister
Author: OpenStack
Author-email: openstack-discuss@lists.openstack.org
License: Apache
Keywords: openstack monitoring storage
Platform: UNKNOWN
Classifier: Development Status :: 5 - Production/Stable
Classifier: License :: OSI Approved :: Apache Software License
Classifier: Topic :: System :: Monitoring
Classifier: Programming Language :: Python
Classifier: Programming Language :: Python :: Implementation :: CPython
Classifier: Programming Language :: Python :: 3 :: Only
Classifier: Programming Language :: Python :: 3
Classifier: Programming Language :: Python :: 3.6
Classifier: Programming Language :: Python :: 3.7
Requires-Python: >=3.6
Requires-Dist: cassandra-driver (>=3.21.0)
Requires-Dist: monasca-common (>=2.16.0)
Requires-Dist: oslo.config (>=5.2.0)
Requires-Dist: oslo.log (>=3.36.0)
Requires-Dist: simplejson (>=3.8.1)
Provides-Extra: cassandra
Requires-Dist: cassandra-driver (>=3.21.0) ; extra == 'cassandra'
Provides-Extra: elasticsearch
Requires-Dist: elasticsearch (<3.0.0,>=2.0.0) ; extra == 'elasticsearch'
Provides-Extra: influxdb
Requires-Dist: influxdb (>=2.9.2) ; extra == 'influxdb'
Provides-Extra: test
Requires-Dist: bandit (>=1.1.0) ; extra == 'test'
Requires-Dist: cassandra-driver (>=3.21.0) ; extra == 'test'
Requires-Dist: coverage (!=4.4,>=4.0) ; extra == 'test'
Requires-Dist: hacking (<3.1.0,>=3.0.1) ; extra == 'test'
Requires-Dist: oslotest (>=3.2.0) ; extra == 'test'
Requires-Dist: pycodestyle (>=2.5.0) ; extra == 'test'
Requires-Dist: stestr (>=1.0.0) ; extra == 'test'
